iterable_tompy/__init__.py
iterable_tompy/exceptions.py
iterable_tompy/first.py
iterable_tompy/head.py
iterable_tompy/indices.py
iterable_tompy/init.py
iterable_tompy/last.py
iterable_tompy/tail.py
iterable_tompy-2025.9.16.21.41.dist-info/METADATA
iterable_tompy-2025.9.16.21.41.dist-info/WHEEL
iterable_tompy-2025.9.16.21.41.dist-info/RECORD
