Metadata-Version: 2.4
Name: iterable-tompy
Version: 2025.9.16.21.41
Summary: Iterables for tompy projects
Author: tompy
Classifier: Development Status :: 3 - Alpha
Classifier: Intended Audience :: Developers
Classifier: License :: OSI Approved :: GNU General Public License v3 (GPLv3)
Classifier: Operating System :: OS Independent
Classifier: Programming Language :: Python :: 3.9
Requires-Python: >=3.9
